{"namedChunkGroups":{"polyfill":{"name":"polyfill","assets":[{"name":"webpack-runtime-0a5a8a40d39bc58694b6.js","size":9100},{"name":"polyfill-8fca69998c1b56bb4653.js","size":82231}],"filteredAssets":0,"assetsSize":91331,"filteredAuxiliaryAssets":2,"auxiliaryAssetsSize":225022},"app":{"name":"app","assets":[{"name":"webpack-runtime-0a5a8a40d39bc58694b6.js","size":9100},{"name":"styles.0b34ffe8ec1ad9342c1f.css","size":532835},{"name":"framework-1fdfb31df7fb1cf2263b.js","size":22603},{"name":"ff106bf9-4c8aca29444178e3a710.js","size":8212},{"name":"bca8bde3-bec26adc296f79c6c723.js","size":6162},{"name":"app-dc5323cc35249e649428.js","size":195367}],"filteredAssets":0,"assetsSize":774279,"filteredAuxiliaryAssets":5,"auxiliaryAssetsSize":843452},"component---node-modules-adobe-gatsby-theme-aio-src-pages-404-md":{"name":"component---node-modules-adobe-gatsby-theme-aio-src-pages-404-md","assets":[{"name":"styles.0b34ffe8ec1ad9342c1f.css","size":532835},{"name":"f5cc1685-5768e2433d68321a2a75.js","size":6143},{"name":"8b61fb39-8d9d16599d59961494d7.js","size":6752},{"name":"7deef1cd-db568229c9ae5080074c.js","size":5530},{"name":"b6f3ea4c-93893a1a9cc3f7053a55.js","size":7066},{"name":"5e65052d-ab560c7f49ce6e61a438.js","size":6030},{"name":"2dee68d8-2581d4c6e40e7ba2c1af.js","size":6607},{"name":"commons-45d0b93d6f0816b185bb.js","size":103104},{"name":"component---node-modules-adobe-gatsby-theme-aio-src-pages-404-md-38c54a7cc6735dfbf45d.js","size":1099}],"filteredAssets":0,"assetsSize":675166,"filteredAuxiliaryAssets":8,"auxiliaryAssetsSize":376731},"component---src-pages-index-md":{"name":"component---src-pages-index-md","assets":[{"name":"styles.0b34ffe8ec1ad9342c1f.css","size":532835},{"name":"f5cc1685-5768e2433d68321a2a75.js","size":6143},{"name":"8b61fb39-8d9d16599d59961494d7.js","size":6752},{"name":"7deef1cd-db568229c9ae5080074c.js","size":5530},{"name":"b6f3ea4c-93893a1a9cc3f7053a55.js","size":7066},{"name":"5e65052d-ab560c7f49ce6e61a438.js","size":6030},{"name":"2dee68d8-2581d4c6e40e7ba2c1af.js","size":6607},{"name":"commons-45d0b93d6f0816b185bb.js","size":103104},{"name":"component---src-pages-index-md-0453ae767c0509a3b501.js","size":6486}],"filteredAssets":0,"assetsSize":680553,"filteredAuxiliaryAssets":8,"auxiliaryAssetsSize":383885},"component---src-pages-xmp-namespaces-crs-index-md":{"name":"component---src-pages-xmp-namespaces-crs-index-md","assets":[{"name":"styles.0b34ffe8ec1ad9342c1f.css","size":532835},{"name":"f5cc1685-5768e2433d68321a2a75.js","size":6143},{"name":"8b61fb39-8d9d16599d59961494d7.js","size":6752},{"name":"7deef1cd-db568229c9ae5080074c.js","size":5530},{"name":"b6f3ea4c-93893a1a9cc3f7053a55.js","size":7066},{"name":"5e65052d-ab560c7f49ce6e61a438.js","size":6030},{"name":"2dee68d8-2581d4c6e40e7ba2c1af.js","size":6607},{"name":"commons-45d0b93d6f0816b185bb.js","size":103104},{"name":"component---src-pages-xmp-namespaces-crs-index-md-3a4495462ff30f9baf54.js","size":15649}],"filteredAssets":0,"assetsSize":689716,"filteredAuxiliaryAssets":8,"auxiliaryAssetsSize":404917},"component---src-pages-xmp-namespaces-dc-index-md":{"name":"component---src-pages-xmp-namespaces-dc-index-md","assets":[{"name":"styles.0b34ffe8ec1ad9342c1f.css","size":532835},{"name":"f5cc1685-5768e2433d68321a2a75.js","size":6143},{"name":"8b61fb39-8d9d16599d59961494d7.js","size":6752},{"name":"7deef1cd-db568229c9ae5080074c.js","size":5530},{"name":"b6f3ea4c-93893a1a9cc3f7053a55.js","size":7066},{"name":"5e65052d-ab560c7f49ce6e61a438.js","size":6030},{"name":"2dee68d8-2581d4c6e40e7ba2c1af.js","size":6607},{"name":"commons-45d0b93d6f0816b185bb.js","size":103104},{"name":"component---src-pages-xmp-namespaces-dc-index-md-2b56534631f4ff9b99b0.js","size":11644}],"filteredAssets":0,"assetsSize":685711,"filteredAuxiliaryAssets":8,"auxiliaryAssetsSize":393260},"component---src-pages-xmp-namespaces-exif-index-md":{"name":"component---src-pages-xmp-namespaces-exif-index-md","assets":[{"name":"styles.0b34ffe8ec1ad9342c1f.css","size":532835},{"name":"f5cc1685-5768e2433d68321a2a75.js","size":6143},{"name":"8b61fb39-8d9d16599d59961494d7.js","size":6752},{"name":"7deef1cd-db568229c9ae5080074c.js","size":5530},{"name":"b6f3ea4c-93893a1a9cc3f7053a55.js","size":7066},{"name":"5e65052d-ab560c7f49ce6e61a438.js","size":6030},{"name":"2dee68d8-2581d4c6e40e7ba2c1af.js","size":6607},{"name":"commons-45d0b93d6f0816b185bb.js","size":103104},{"name":"component---src-pages-xmp-namespaces-exif-index-md-6c7f781bbb7b85af0870.js","size":37364}],"filteredAssets":0,"assetsSize":711431,"filteredAuxiliaryAssets":8,"auxiliaryAssetsSize":441122},"component---src-pages-xmp-namespaces-index-md":{"name":"component---src-pages-xmp-namespaces-index-md","assets":[{"name":"styles.0b34ffe8ec1ad9342c1f.css","size":532835},{"name":"f5cc1685-5768e2433d68321a2a75.js","size":6143},{"name":"8b61fb39-8d9d16599d59961494d7.js","size":6752},{"name":"7deef1cd-db568229c9ae5080074c.js","size":5530},{"name":"b6f3ea4c-93893a1a9cc3f7053a55.js","size":7066},{"name":"5e65052d-ab560c7f49ce6e61a438.js","size":6030},{"name":"2dee68d8-2581d4c6e40e7ba2c1af.js","size":6607},{"name":"commons-45d0b93d6f0816b185bb.js","size":103104},{"name":"component---src-pages-xmp-namespaces-index-md-b63ac99758a50ca9c2e2.js","size":4108}],"filteredAssets":0,"assetsSize":678175,"filteredAuxiliaryAssets":8,"auxiliaryAssetsSize":380729},"component---src-pages-xmp-namespaces-iptc-4-xmp-core-index-md":{"name":"component---src-pages-xmp-namespaces-iptc-4-xmp-core-index-md","assets":[{"name":"styles.0b34ffe8ec1ad9342c1f.css","size":532835},{"name":"f5cc1685-5768e2433d68321a2a75.js","size":6143},{"name":"8b61fb39-8d9d16599d59961494d7.js","size":6752},{"name":"7deef1cd-db568229c9ae5080074c.js","size":5530},{"name":"b6f3ea4c-93893a1a9cc3f7053a55.js","size":7066},{"name":"5e65052d-ab560c7f49ce6e61a438.js","size":6030},{"name":"2dee68d8-2581d4c6e40e7ba2c1af.js","size":6607},{"name":"commons-45d0b93d6f0816b185bb.js","size":103104},{"name":"component---src-pages-xmp-namespaces-iptc-4-xmp-core-index-md-b0633949ccd76ac83c6d.js","size":4695}],"filteredAssets":0,"assetsSize":678762,"filteredAuxiliaryAssets":8,"auxiliaryAssetsSize":382348},"component---src-pages-xmp-namespaces-pdf-index-md":{"name":"component---src-pages-xmp-namespaces-pdf-index-md","assets":[{"name":"styles.0b34ffe8ec1ad9342c1f.css","size":532835},{"name":"f5cc1685-5768e2433d68321a2a75.js","size":6143},{"name":"8b61fb39-8d9d16599d59961494d7.js","size":6752},{"name":"7deef1cd-db568229c9ae5080074c.js","size":5530},{"name":"b6f3ea4c-93893a1a9cc3f7053a55.js","size":7066},{"name":"5e65052d-ab560c7f49ce6e61a438.js","size":6030},{"name":"2dee68d8-2581d4c6e40e7ba2c1af.js","size":6607},{"name":"commons-45d0b93d6f0816b185bb.js","size":103104},{"name":"component---src-pages-xmp-namespaces-pdf-index-md-2c5944b4eb3013016349.js","size":2619}],"filteredAssets":0,"assetsSize":676686,"filteredAuxiliaryAssets":8,"auxiliaryAssetsSize":379603},"component---src-pages-xmp-namespaces-photoshop-index-md":{"name":"component---src-pages-xmp-namespaces-photoshop-index-md","assets":[{"name":"styles.0b34ffe8ec1ad9342c1f.css","size":532835},{"name":"f5cc1685-5768e2433d68321a2a75.js","size":6143},{"name":"8b61fb39-8d9d16599d59961494d7.js","size":6752},{"name":"7deef1cd-db568229c9ae5080074c.js","size":5530},{"name":"b6f3ea4c-93893a1a9cc3f7053a55.js","size":7066},{"name":"5e65052d-ab560c7f49ce6e61a438.js","size":6030},{"name":"2dee68d8-2581d4c6e40e7ba2c1af.js","size":6607},{"name":"commons-45d0b93d6f0816b185bb.js","size":103104},{"name":"component---src-pages-xmp-namespaces-photoshop-index-md-eccb62d5c0cf03936d9e.js","size":8105}],"filteredAssets":0,"assetsSize":682172,"filteredAuxiliaryAssets":8,"auxiliaryAssetsSize":390181},"component---src-pages-xmp-namespaces-tiff-index-md":{"name":"component---src-pages-xmp-namespaces-tiff-index-md","assets":[{"name":"styles.0b34ffe8ec1ad9342c1f.css","size":532835},{"name":"f5cc1685-5768e2433d68321a2a75.js","size":6143},{"name":"8b61fb39-8d9d16599d59961494d7.js","size":6752},{"name":"7deef1cd-db568229c9ae5080074c.js","size":5530},{"name":"b6f3ea4c-93893a1a9cc3f7053a55.js","size":7066},{"name":"5e65052d-ab560c7f49ce6e61a438.js","size":6030},{"name":"2dee68d8-2581d4c6e40e7ba2c1af.js","size":6607},{"name":"commons-45d0b93d6f0816b185bb.js","size":103104},{"name":"component---src-pages-xmp-namespaces-tiff-index-md-990d6895bce9153ae157.js","size":12194}],"filteredAssets":0,"assetsSize":686261,"filteredAuxiliaryAssets":8,"auxiliaryAssetsSize":396886},"component---src-pages-xmp-namespaces-xmp-bj-index-md":{"name":"component---src-pages-xmp-namespaces-xmp-bj-index-md","assets":[{"name":"styles.0b34ffe8ec1ad9342c1f.css","size":532835},{"name":"f5cc1685-5768e2433d68321a2a75.js","size":6143},{"name":"8b61fb39-8d9d16599d59961494d7.js","size":6752},{"name":"7deef1cd-db568229c9ae5080074c.js","size":5530},{"name":"b6f3ea4c-93893a1a9cc3f7053a55.js","size":7066},{"name":"5e65052d-ab560c7f49ce6e61a438.js","size":6030},{"name":"2dee68d8-2581d4c6e40e7ba2c1af.js","size":6607},{"name":"commons-45d0b93d6f0816b185bb.js","size":103104},{"name":"component---src-pages-xmp-namespaces-xmp-bj-index-md-fed258d302f0b5df5fa7.js","size":2100}],"filteredAssets":0,"assetsSize":676167,"filteredAuxiliaryAssets":8,"auxiliaryAssetsSize":378138},"component---src-pages-xmp-namespaces-xmp-data-types-ancestor-index-md":{"name":"component---src-pages-xmp-namespaces-xmp-data-types-ancestor-index-md","assets":[{"name":"styles.0b34ffe8ec1ad9342c1f.css","size":532835},{"name":"f5cc1685-5768e2433d68321a2a75.js","size":6143},{"name":"8b61fb39-8d9d16599d59961494d7.js","size":6752},{"name":"7deef1cd-db568229c9ae5080074c.js","size":5530},{"name":"b6f3ea4c-93893a1a9cc3f7053a55.js","size":7066},{"name":"5e65052d-ab560c7f49ce6e61a438.js","size":6030},{"name":"2dee68d8-2581d4c6e40e7ba2c1af.js","size":6607},{"name":"commons-45d0b93d6f0816b185bb.js","size":103104},{"name":"component---src-pages-xmp-namespaces-xmp-data-types-ancestor-index-md-0c32c298abc8b31692f7.js","size":1685}],"filteredAssets":0,"assetsSize":675752,"filteredAuxiliaryAssets":8,"auxiliaryAssetsSize":377727},"component---src-pages-xmp-namespaces-xmp-data-types-beat-splice-stretch-index-md":{"name":"component---src-pages-xmp-namespaces-xmp-data-types-beat-splice-stretch-index-md","assets":[{"name":"styles.0b34ffe8ec1ad9342c1f.css","size":532835},{"name":"f5cc1685-5768e2433d68321a2a75.js","size":6143},{"name":"8b61fb39-8d9d16599d59961494d7.js","size":6752},{"name":"7deef1cd-db568229c9ae5080074c.js","size":5530},{"name":"b6f3ea4c-93893a1a9cc3f7053a55.js","size":7066},{"name":"5e65052d-ab560c7f49ce6e61a438.js","size":6030},{"name":"2dee68d8-2581d4c6e40e7ba2c1af.js","size":6607},{"name":"commons-45d0b93d6f0816b185bb.js","size":103104},{"name":"component---src-pages-xmp-namespaces-xmp-data-types-beat-splice-stretch-index-md-171776fe0ce22f5103ce.js","size":2515}],"filteredAssets":0,"assetsSize":676582,"filteredAuxiliaryAssets":8,"auxiliaryAssetsSize":379206},"component---src-pages-xmp-namespaces-xmp-data-types-cfa-pattern-index-md":{"name":"component---src-pages-xmp-namespaces-xmp-data-types-cfa-pattern-index-md","assets":[{"name":"styles.0b34ffe8ec1ad9342c1f.css","size":532835},{"name":"f5cc1685-5768e2433d68321a2a75.js","size":6143},{"name":"8b61fb39-8d9d16599d59961494d7.js","size":6752},{"name":"7deef1cd-db568229c9ae5080074c.js","size":5530},{"name":"b6f3ea4c-93893a1a9cc3f7053a55.js","size":7066},{"name":"5e65052d-ab560c7f49ce6e61a438.js","size":6030},{"name":"2dee68d8-2581d4c6e40e7ba2c1af.js","size":6607},{"name":"commons-45d0b93d6f0816b185bb.js","size":103104},{"name":"component---src-pages-xmp-namespaces-xmp-data-types-cfa-pattern-index-md-c38ac3c4a9c1f9b3ca17.js","size":2435}],"filteredAssets":0,"assetsSize":676502,"filteredAuxiliaryAssets":8,"auxiliaryAssetsSize":379198},"component---src-pages-xmp-namespaces-xmp-data-types-colorant-index-md":{"name":"component---src-pages-xmp-namespaces-xmp-data-types-colorant-index-md","assets":[{"name":"styles.0b34ffe8ec1ad9342c1f.css","size":532835},{"name":"f5cc1685-5768e2433d68321a2a75.js","size":6143},{"name":"8b61fb39-8d9d16599d59961494d7.js","size":6752},{"name":"7deef1cd-db568229c9ae5080074c.js","size":5530},{"name":"b6f3ea4c-93893a1a9cc3f7053a55.js","size":7066},{"name":"5e65052d-ab560c7f49ce6e61a438.js","size":6030},{"name":"2dee68d8-2581d4c6e40e7ba2c1af.js","size":6607},{"name":"commons-45d0b93d6f0816b185bb.js","size":103104},{"name":"component---src-pages-xmp-namespaces-xmp-data-types-colorant-index-md-b70bfa6240d80b7ed50e.js","size":5725}],"filteredAssets":0,"assetsSize":679792,"filteredAuxiliaryAssets":8,"auxiliaryAssetsSize":385765},"component---src-pages-xmp-namespaces-xmp-data-types-contact-info-index-md":{"name":"component---src-pages-xmp-namespaces-xmp-data-types-contact-info-index-md","assets":[{"name":"styles.0b34ffe8ec1ad9342c1f.css","size":532835},{"name":"f5cc1685-5768e2433d68321a2a75.js","size":6143},{"name":"8b61fb39-8d9d16599d59961494d7.js","size":6752},{"name":"7deef1cd-db568229c9ae5080074c.js","size":5530},{"name":"b6f3ea4c-93893a1a9cc3f7053a55.js","size":7066},{"name":"5e65052d-ab560c7f49ce6e61a438.js","size":6030},{"name":"2dee68d8-2581d4c6e40e7ba2c1af.js","size":6607},{"name":"commons-45d0b93d6f0816b185bb.js","size":103104},{"name":"component---src-pages-xmp-namespaces-xmp-data-types-contact-info-index-md-80501db09dd99c03ba5d.js","size":4309}],"filteredAssets":0,"assetsSize":678376,"filteredAuxiliaryAssets":8,"auxiliaryAssetsSize":382588},"component---src-pages-xmp-namespaces-xmp-data-types-cue-point-param-index-md":{"name":"component---src-pages-xmp-namespaces-xmp-data-types-cue-point-param-index-md","assets":[{"name":"styles.0b34ffe8ec1ad9342c1f.css","size":532835},{"name":"f5cc1685-5768e2433d68321a2a75.js","size":6143},{"name":"8b61fb39-8d9d16599d59961494d7.js","size":6752},{"name":"7deef1cd-db568229c9ae5080074c.js","size":5530},{"name":"b6f3ea4c-93893a1a9cc3f7053a55.js","size":7066},{"name":"5e65052d-ab560c7f49ce6e61a438.js","size":6030},{"name":"2dee68d8-2581d4c6e40e7ba2c1af.js","size":6607},{"name":"commons-45d0b93d6f0816b185bb.js","size":103104},{"name":"component---src-pages-xmp-namespaces-xmp-data-types-cue-point-param-index-md-c79d002dc0b7805814b4.js","size":1975}],"filteredAssets":0,"assetsSize":676042,"filteredAuxiliaryAssets":8,"auxiliaryAssetsSize":378406},"component---src-pages-xmp-namespaces-xmp-data-types-device-settings-index-md":{"name":"component---src-pages-xmp-namespaces-xmp-data-types-device-settings-index-md","assets":[{"name":"styles.0b34ffe8ec1ad9342c1f.css","size":532835},{"name":"f5cc1685-5768e2433d68321a2a75.js","size":6143},{"name":"8b61fb39-8d9d16599d59961494d7.js","size":6752},{"name":"7deef1cd-db568229c9ae5080074c.js","size":5530},{"name":"b6f3ea4c-93893a1a9cc3f7053a55.js","size":7066},{"name":"5e65052d-ab560c7f49ce6e61a438.js","size":6030},{"name":"2dee68d8-2581d4c6e40e7ba2c1af.js","size":6607},{"name":"commons-45d0b93d6f0816b185bb.js","size":103104},{"name":"component---src-pages-xmp-namespaces-xmp-data-types-device-settings-index-md-3bc80eb81bbdf60e2628.js","size":2208}],"filteredAssets":0,"assetsSize":676275,"filteredAuxiliaryAssets":8,"auxiliaryAssetsSize":378905},"component---src-pages-xmp-namespaces-xmp-data-types-dimensions-index-md":{"name":"component---src-pages-xmp-namespaces-xmp-data-types-dimensions-index-md","assets":[{"name":"styles.0b34ffe8ec1ad9342c1f.css","size":532835},{"name":"f5cc1685-5768e2433d68321a2a75.js","size":6143},{"name":"8b61fb39-8d9d16599d59961494d7.js","size":6752},{"name":"7deef1cd-db568229c9ae5080074c.js","size":5530},{"name":"b6f3ea4c-93893a1a9cc3f7053a55.js","size":7066},{"name":"5e65052d-ab560c7f49ce6e61a438.js","size":6030},{"name":"2dee68d8-2581d4c6e40e7ba2c1af.js","size":6607},{"name":"commons-45d0b93d6f0816b185bb.js","size":103104},{"name":"component---src-pages-xmp-namespaces-xmp-data-types-dimensions-index-md-0657019883970b58533d.js","size":2244}],"filteredAssets":0,"assetsSize":676311,"filteredAuxiliaryAssets":8,"auxiliaryAssetsSize":378933},"component---src-pages-xmp-namespaces-xmp-data-types-flash-index-md":{"name":"component---src-pages-xmp-namespaces-xmp-data-types-flash-index-md","assets":[{"name":"styles.0b34ffe8ec1ad9342c1f.css","size":532835},{"name":"f5cc1685-5768e2433d68321a2a75.js","size":6143},{"name":"8b61fb39-8d9d16599d59961494d7.js","size":6752},{"name":"7deef1cd-db568229c9ae5080074c.js","size":5530},{"name":"b6f3ea4c-93893a1a9cc3f7053a55.js","size":7066},{"name":"5e65052d-ab560c7f49ce6e61a438.js","size":6030},{"name":"2dee68d8-2581d4c6e40e7ba2c1af.js","size":6607},{"name":"commons-45d0b93d6f0816b185bb.js","size":103104},{"name":"component---src-pages-xmp-namespaces-xmp-data-types-flash-index-md-653ebd5152fa1ce74f5c.js","size":3398}],"filteredAssets":0,"assetsSize":677465,"filteredAuxiliaryAssets":8,"auxiliaryAssetsSize":380957},"component---src-pages-xmp-namespaces-xmp-data-types-font-index-md":{"name":"component---src-pages-xmp-namespaces-xmp-data-types-font-index-md","assets":[{"name":"styles.0b34ffe8ec1ad9342c1f.css","size":532835},{"name":"f5cc1685-5768e2433d68321a2a75.js","size":6143},{"name":"8b61fb39-8d9d16599d59961494d7.js","size":6752},{"name":"7deef1cd-db568229c9ae5080074c.js","size":5530},{"name":"b6f3ea4c-93893a1a9cc3f7053a55.js","size":7066},{"name":"5e65052d-ab560c7f49ce6e61a438.js","size":6030},{"name":"2dee68d8-2581d4c6e40e7ba2c1af.js","size":6607},{"name":"commons-45d0b93d6f0816b185bb.js","size":103104},{"name":"component---src-pages-xmp-namespaces-xmp-data-types-font-index-md-e38f7cb1698388dc7443.js","size":4615}],"filteredAssets":0,"assetsSize":678682,"filteredAuxiliaryAssets":8,"auxiliaryAssetsSize":383043},"component---src-pages-xmp-namespaces-xmp-data-types-index-md":{"name":"component---src-pages-xmp-namespaces-xmp-data-types-index-md","assets":[{"name":"styles.0b34ffe8ec1ad9342c1f.css","size":532835},{"name":"f5cc1685-5768e2433d68321a2a75.js","size":6143},{"name":"8b61fb39-8d9d16599d59961494d7.js","size":6752},{"name":"7deef1cd-db568229c9ae5080074c.js","size":5530},{"name":"b6f3ea4c-93893a1a9cc3f7053a55.js","size":7066},{"name":"5e65052d-ab560c7f49ce6e61a438.js","size":6030},{"name":"2dee68d8-2581d4c6e40e7ba2c1af.js","size":6607},{"name":"commons-45d0b93d6f0816b185bb.js","size":103104},{"name":"component---src-pages-xmp-namespaces-xmp-data-types-index-md-b7af4798a9188a6c19a4.js","size":24983}],"filteredAssets":0,"assetsSize":699050,"filteredAuxiliaryAssets":8,"auxiliaryAssetsSize":413173},"component---src-pages-xmp-namespaces-xmp-data-types-job-index-md":{"name":"component---src-pages-xmp-namespaces-xmp-data-types-job-index-md","assets":[{"name":"styles.0b34ffe8ec1ad9342c1f.css","size":532835},{"name":"f5cc1685-5768e2433d68321a2a75.js","size":6143},{"name":"8b61fb39-8d9d16599d59961494d7.js","size":6752},{"name":"7deef1cd-db568229c9ae5080074c.js","size":5530},{"name":"b6f3ea4c-93893a1a9cc3f7053a55.js","size":7066},{"name":"5e65052d-ab560c7f49ce6e61a438.js","size":6030},{"name":"2dee68d8-2581d4c6e40e7ba2c1af.js","size":6607},{"name":"commons-45d0b93d6f0816b185bb.js","size":103104},{"name":"component---src-pages-xmp-namespaces-xmp-data-types-job-index-md-3a4fed1c939d17a41bca.js","size":2321}],"filteredAssets":0,"assetsSize":676388,"filteredAuxiliaryAssets":8,"auxiliaryAssetsSize":378993},"component---src-pages-xmp-namespaces-xmp-data-types-layer-index-md":{"name":"component---src-pages-xmp-namespaces-xmp-data-types-layer-index-md","assets":[{"name":"styles.0b34ffe8ec1ad9342c1f.css","size":532835},{"name":"f5cc1685-5768e2433d68321a2a75.js","size":6143},{"name":"8b61fb39-8d9d16599d59961494d7.js","size":6752},{"name":"7deef1cd-db568229c9ae5080074c.js","size":5530},{"name":"b6f3ea4c-93893a1a9cc3f7053a55.js","size":7066},{"name":"5e65052d-ab560c7f49ce6e61a438.js","size":6030},{"name":"2dee68d8-2581d4c6e40e7ba2c1af.js","size":6607},{"name":"commons-45d0b93d6f0816b185bb.js","size":103104},{"name":"component---src-pages-xmp-namespaces-xmp-data-types-layer-index-md-b063958500c95872d8a0.js","size":1999}],"filteredAssets":0,"assetsSize":676066,"filteredAuxiliaryAssets":8,"auxiliaryAssetsSize":378358},"component---src-pages-xmp-namespaces-xmp-data-types-marker-index-md":{"name":"component---src-pages-xmp-namespaces-xmp-data-types-marker-index-md","assets":[{"name":"styles.0b34ffe8ec1ad9342c1f.css","size":532835},{"name":"f5cc1685-5768e2433d68321a2a75.js","size":6143},{"name":"8b61fb39-8d9d16599d59961494d7.js","size":6752},{"name":"7deef1cd-db568229c9ae5080074c.js","size":5530},{"name":"b6f3ea4c-93893a1a9cc3f7053a55.js","size":7066},{"name":"5e65052d-ab560c7f49ce6e61a438.js","size":6030},{"name":"2dee68d8-2581d4c6e40e7ba2c1af.js","size":6607},{"name":"commons-45d0b93d6f0816b185bb.js","size":103104},{"name":"component---src-pages-xmp-namespaces-xmp-data-types-marker-index-md-a98ef0c3e796066b8dc5.js","size":6137}],"filteredAssets":0,"assetsSize":680204,"filteredAuxiliaryAssets":8,"auxiliaryAssetsSize":385709},"component---src-pages-xmp-namespaces-xmp-data-types-media-index-md":{"name":"component---src-pages-xmp-namespaces-xmp-data-types-media-index-md","assets":[{"name":"styles.0b34ffe8ec1ad9342c1f.css","size":532835},{"name":"f5cc1685-5768e2433d68321a2a75.js","size":6143},{"name":"8b61fb39-8d9d16599d59961494d7.js","size":6752},{"name":"7deef1cd-db568229c9ae5080074c.js","size":5530},{"name":"b6f3ea4c-93893a1a9cc3f7053a55.js","size":7066},{"name":"5e65052d-ab560c7f49ce6e61a438.js","size":6030},{"name":"2dee68d8-2581d4c6e40e7ba2c1af.js","size":6607},{"name":"commons-45d0b93d6f0816b185bb.js","size":103104},{"name":"component---src-pages-xmp-namespaces-xmp-data-types-media-index-md-5c95f599fbc1dbed5ced.js","size":3475}],"filteredAssets":0,"assetsSize":677542,"filteredAuxiliaryAssets":8,"auxiliaryAssetsSize":381106},"component---src-pages-xmp-namespaces-xmp-data-types-oecf-sfr-index-md":{"name":"component---src-pages-xmp-namespaces-xmp-data-types-oecf-sfr-index-md","assets":[{"name":"styles.0b34ffe8ec1ad9342c1f.css","size":532835},{"name":"f5cc1685-5768e2433d68321a2a75.js","size":6143},{"name":"8b61fb39-8d9d16599d59961494d7.js","size":6752},{"name":"7deef1cd-db568229c9ae5080074c.js","size":5530},{"name":"b6f3ea4c-93893a1a9cc3f7053a55.js","size":7066},{"name":"5e65052d-ab560c7f49ce6e61a438.js","size":6030},{"name":"2dee68d8-2581d4c6e40e7ba2c1af.js","size":6607},{"name":"commons-45d0b93d6f0816b185bb.js","size":103104},{"name":"component---src-pages-xmp-namespaces-xmp-data-types-oecf-sfr-index-md-351f87403fcc92456b6c.js","size":2771}],"filteredAssets":0,"assetsSize":676838,"filteredAuxiliaryAssets":8,"auxiliaryAssetsSize":379871},"component---src-pages-xmp-namespaces-xmp-data-types-project-link-index-md":{"name":"component---src-pages-xmp-namespaces-xmp-data-types-project-link-index-md","assets":[{"name":"styles.0b34ffe8ec1ad9342c1f.css","size":532835},{"name":"f5cc1685-5768e2433d68321a2a75.js","size":6143},{"name":"8b61fb39-8d9d16599d59961494d7.js","size":6752},{"name":"7deef1cd-db568229c9ae5080074c.js","size":5530},{"name":"b6f3ea4c-93893a1a9cc3f7053a55.js","size":7066},{"name":"5e65052d-ab560c7f49ce6e61a438.js","size":6030},{"name":"2dee68d8-2581d4c6e40e7ba2c1af.js","size":6607},{"name":"commons-45d0b93d6f0816b185bb.js","size":103104},{"name":"component---src-pages-xmp-namespaces-xmp-data-types-project-link-index-md-7a8f6389f419a346d751.js","size":2011}],"filteredAssets":0,"assetsSize":676078,"filteredAuxiliaryAssets":8,"auxiliaryAssetsSize":378384},"component---src-pages-xmp-namespaces-xmp-data-types-resample-stretch-index-md":{"name":"component---src-pages-xmp-namespaces-xmp-data-types-resample-stretch-index-md","assets":[{"name":"styles.0b34ffe8ec1ad9342c1f.css","size":532835},{"name":"f5cc1685-5768e2433d68321a2a75.js","size":6143},{"name":"8b61fb39-8d9d16599d59961494d7.js","size":6752},{"name":"7deef1cd-db568229c9ae5080074c.js","size":5530},{"name":"b6f3ea4c-93893a1a9cc3f7053a55.js","size":7066},{"name":"5e65052d-ab560c7f49ce6e61a438.js","size":6030},{"name":"2dee68d8-2581d4c6e40e7ba2c1af.js","size":6607},{"name":"commons-45d0b93d6f0816b185bb.js","size":103104},{"name":"component---src-pages-xmp-namespaces-xmp-data-types-resample-stretch-index-md-b7b4981255b4b1b22f57.js","size":1714}],"filteredAssets":0,"assetsSize":675781,"filteredAuxiliaryAssets":8,"auxiliaryAssetsSize":377776},"component---src-pages-xmp-namespaces-xmp-data-types-resource-event-index-md":{"name":"component---src-pages-xmp-namespaces-xmp-data-types-resource-event-index-md","assets":[{"name":"styles.0b34ffe8ec1ad9342c1f.css","size":532835},{"name":"f5cc1685-5768e2433d68321a2a75.js","size":6143},{"name":"8b61fb39-8d9d16599d59961494d7.js","size":6752},{"name":"7deef1cd-db568229c9ae5080074c.js","size":5530},{"name":"b6f3ea4c-93893a1a9cc3f7053a55.js","size":7066},{"name":"5e65052d-ab560c7f49ce6e61a438.js","size":6030},{"name":"2dee68d8-2581d4c6e40e7ba2c1af.js","size":6607},{"name":"commons-45d0b93d6f0816b185bb.js","size":103104},{"name":"component---src-pages-xmp-namespaces-xmp-data-types-resource-event-index-md-0a1153b9b86a3e2c0ba2.js","size":4719}],"filteredAssets":0,"assetsSize":678786,"filteredAuxiliaryAssets":8,"auxiliaryAssetsSize":382893},"component---src-pages-xmp-namespaces-xmp-data-types-resource-ref-index-md":{"name":"component---src-pages-xmp-namespaces-xmp-data-types-resource-ref-index-md","assets":[{"name":"styles.0b34ffe8ec1ad9342c1f.css","size":532835},{"name":"f5cc1685-5768e2433d68321a2a75.js","size":6143},{"name":"8b61fb39-8d9d16599d59961494d7.js","size":6752},{"name":"7deef1cd-db568229c9ae5080074c.js","size":5530},{"name":"b6f3ea4c-93893a1a9cc3f7053a55.js","size":7066},{"name":"5e65052d-ab560c7f49ce6e61a438.js","size":6030},{"name":"2dee68d8-2581d4c6e40e7ba2c1af.js","size":6607},{"name":"commons-45d0b93d6f0816b185bb.js","size":103104},{"name":"component---src-pages-xmp-namespaces-xmp-data-types-resource-ref-index-md-391552cc029c1f71d0c5.js","size":7449}],"filteredAssets":0,"assetsSize":681516,"filteredAuxiliaryAssets":8,"auxiliaryAssetsSize":388342},"component---src-pages-xmp-namespaces-xmp-data-types-thumbnails-index-md":{"name":"component---src-pages-xmp-namespaces-xmp-data-types-thumbnails-index-md","assets":[{"name":"styles.0b34ffe8ec1ad9342c1f.css","size":532835},{"name":"f5cc1685-5768e2433d68321a2a75.js","size":6143},{"name":"8b61fb39-8d9d16599d59961494d7.js","size":6752},{"name":"7deef1cd-db568229c9ae5080074c.js","size":5530},{"name":"b6f3ea4c-93893a1a9cc3f7053a55.js","size":7066},{"name":"5e65052d-ab560c7f49ce6e61a438.js","size":6030},{"name":"2dee68d8-2581d4c6e40e7ba2c1af.js","size":6607},{"name":"commons-45d0b93d6f0816b185bb.js","size":103104},{"name":"component---src-pages-xmp-namespaces-xmp-data-types-thumbnails-index-md-ffc3fb5ab5e0ba996685.js","size":2692}],"filteredAssets":0,"assetsSize":676759,"filteredAuxiliaryAssets":8,"auxiliaryAssetsSize":379703},"component---src-pages-xmp-namespaces-xmp-data-types-time-index-md":{"name":"component---src-pages-xmp-namespaces-xmp-data-types-time-index-md","assets":[{"name":"styles.0b34ffe8ec1ad9342c1f.css","size":532835},{"name":"f5cc1685-5768e2433d68321a2a75.js","size":6143},{"name":"8b61fb39-8d9d16599d59961494d7.js","size":6752},{"name":"7deef1cd-db568229c9ae5080074c.js","size":5530},{"name":"b6f3ea4c-93893a1a9cc3f7053a55.js","size":7066},{"name":"5e65052d-ab560c7f49ce6e61a438.js","size":6030},{"name":"2dee68d8-2581d4c6e40e7ba2c1af.js","size":6607},{"name":"commons-45d0b93d6f0816b185bb.js","size":103104},{"name":"component---src-pages-xmp-namespaces-xmp-data-types-time-index-md-494717b08aa09388c84c.js","size":2253}],"filteredAssets":0,"assetsSize":676320,"filteredAuxiliaryAssets":8,"auxiliaryAssetsSize":378611},"component---src-pages-xmp-namespaces-xmp-data-types-time-scale-stretch-index-md":{"name":"component---src-pages-xmp-namespaces-xmp-data-types-time-scale-stretch-index-md","assets":[{"name":"styles.0b34ffe8ec1ad9342c1f.css","size":532835},{"name":"f5cc1685-5768e2433d68321a2a75.js","size":6143},{"name":"8b61fb39-8d9d16599d59961494d7.js","size":6752},{"name":"7deef1cd-db568229c9ae5080074c.js","size":5530},{"name":"b6f3ea4c-93893a1a9cc3f7053a55.js","size":7066},{"name":"5e65052d-ab560c7f49ce6e61a438.js","size":6030},{"name":"2dee68d8-2581d4c6e40e7ba2c1af.js","size":6607},{"name":"commons-45d0b93d6f0816b185bb.js","size":103104},{"name":"component---src-pages-xmp-namespaces-xmp-data-types-time-scale-stretch-index-md-ae2b8c9f55aa537258b1.js","size":2328}],"filteredAssets":0,"assetsSize":676395,"filteredAuxiliaryAssets":8,"auxiliaryAssetsSize":379028},"component---src-pages-xmp-namespaces-xmp-data-types-timecode-index-md":{"name":"component---src-pages-xmp-namespaces-xmp-data-types-timecode-index-md","assets":[{"name":"styles.0b34ffe8ec1ad9342c1f.css","size":532835},{"name":"f5cc1685-5768e2433d68321a2a75.js","size":6143},{"name":"8b61fb39-8d9d16599d59961494d7.js","size":6752},{"name":"7deef1cd-db568229c9ae5080074c.js","size":5530},{"name":"b6f3ea4c-93893a1a9cc3f7053a55.js","size":7066},{"name":"5e65052d-ab560c7f49ce6e61a438.js","size":6030},{"name":"2dee68d8-2581d4c6e40e7ba2c1af.js","size":6607},{"name":"commons-45d0b93d6f0816b185bb.js","size":103104},{"name":"component---src-pages-xmp-namespaces-xmp-data-types-timecode-index-md-e70b16e2e55b047c4184.js","size":2765}],"filteredAssets":0,"assetsSize":676832,"filteredAuxiliaryAssets":8,"auxiliaryAssetsSize":379432},"component---src-pages-xmp-namespaces-xmp-data-types-track-index-md":{"name":"component---src-pages-xmp-namespaces-xmp-data-types-track-index-md","assets":[{"name":"styles.0b34ffe8ec1ad9342c1f.css","size":532835},{"name":"f5cc1685-5768e2433d68321a2a75.js","size":6143},{"name":"8b61fb39-8d9d16599d59961494d7.js","size":6752},{"name":"7deef1cd-db568229c9ae5080074c.js","size":5530},{"name":"b6f3ea4c-93893a1a9cc3f7053a55.js","size":7066},{"name":"5e65052d-ab560c7f49ce6e61a438.js","size":6030},{"name":"2dee68d8-2581d4c6e40e7ba2c1af.js","size":6607},{"name":"commons-45d0b93d6f0816b185bb.js","size":103104},{"name":"component---src-pages-xmp-namespaces-xmp-data-types-track-index-md-b70ef51e0a9a06884d06.js","size":2827}],"filteredAssets":0,"assetsSize":676894,"filteredAuxiliaryAssets":8,"auxiliaryAssetsSize":379923},"component---src-pages-xmp-namespaces-xmp-data-types-version-index-md":{"name":"component---src-pages-xmp-namespaces-xmp-data-types-version-index-md","assets":[{"name":"styles.0b34ffe8ec1ad9342c1f.css","size":532835},{"name":"f5cc1685-5768e2433d68321a2a75.js","size":6143},{"name":"8b61fb39-8d9d16599d59961494d7.js","size":6752},{"name":"7deef1cd-db568229c9ae5080074c.js","size":5530},{"name":"b6f3ea4c-93893a1a9cc3f7053a55.js","size":7066},{"name":"5e65052d-ab560c7f49ce6e61a438.js","size":6030},{"name":"2dee68d8-2581d4c6e40e7ba2c1af.js","size":6607},{"name":"commons-45d0b93d6f0816b185bb.js","size":103104},{"name":"component---src-pages-xmp-namespaces-xmp-data-types-version-index-md-df93db3a06bb688f7bbb.js","size":2879}],"filteredAssets":0,"assetsSize":676946,"filteredAuxiliaryAssets":8,"auxiliaryAssetsSize":380198},"component---src-pages-xmp-namespaces-xmp-dm-index-md":{"name":"component---src-pages-xmp-namespaces-xmp-dm-index-md","assets":[{"name":"styles.0b34ffe8ec1ad9342c1f.css","size":532835},{"name":"f5cc1685-5768e2433d68321a2a75.js","size":6143},{"name":"8b61fb39-8d9d16599d59961494d7.js","size":6752},{"name":"7deef1cd-db568229c9ae5080074c.js","size":5530},{"name":"b6f3ea4c-93893a1a9cc3f7053a55.js","size":7066},{"name":"5e65052d-ab560c7f49ce6e61a438.js","size":6030},{"name":"2dee68d8-2581d4c6e40e7ba2c1af.js","size":6607},{"name":"commons-45d0b93d6f0816b185bb.js","size":103104},{"name":"component---src-pages-xmp-namespaces-xmp-dm-index-md-09875a239b84bead8d34.js","size":32111}],"filteredAssets":0,"assetsSize":706178,"filteredAuxiliaryAssets":8,"auxiliaryAssetsSize":434200},"component---src-pages-xmp-namespaces-xmp-index-md":{"name":"component---src-pages-xmp-namespaces-xmp-index-md","assets":[{"name":"styles.0b34ffe8ec1ad9342c1f.css","size":532835},{"name":"f5cc1685-5768e2433d68321a2a75.js","size":6143},{"name":"8b61fb39-8d9d16599d59961494d7.js","size":6752},{"name":"7deef1cd-db568229c9ae5080074c.js","size":5530},{"name":"b6f3ea4c-93893a1a9cc3f7053a55.js","size":7066},{"name":"5e65052d-ab560c7f49ce6e61a438.js","size":6030},{"name":"2dee68d8-2581d4c6e40e7ba2c1af.js","size":6607},{"name":"commons-45d0b93d6f0816b185bb.js","size":103104},{"name":"component---src-pages-xmp-namespaces-xmp-index-md-3837f28aee7828a8bd75.js","size":6402}],"filteredAssets":0,"assetsSize":680469,"filteredAuxiliaryAssets":8,"auxiliaryAssetsSize":385332},"component---src-pages-xmp-namespaces-xmp-mm-index-md":{"name":"component---src-pages-xmp-namespaces-xmp-mm-index-md","assets":[{"name":"styles.0b34ffe8ec1ad9342c1f.css","size":532835},{"name":"f5cc1685-5768e2433d68321a2a75.js","size":6143},{"name":"8b61fb39-8d9d16599d59961494d7.js","size":6752},{"name":"7deef1cd-db568229c9ae5080074c.js","size":5530},{"name":"b6f3ea4c-93893a1a9cc3f7053a55.js","size":7066},{"name":"5e65052d-ab560c7f49ce6e61a438.js","size":6030},{"name":"2dee68d8-2581d4c6e40e7ba2c1af.js","size":6607},{"name":"commons-45d0b93d6f0816b185bb.js","size":103104},{"name":"component---src-pages-xmp-namespaces-xmp-mm-index-md-babc619e51757d629231.js","size":10796}],"filteredAssets":0,"assetsSize":684863,"filteredAuxiliaryAssets":8,"auxiliaryAssetsSize":391720},"component---src-pages-xmp-namespaces-xmp-rights-index-md":{"name":"component---src-pages-xmp-namespaces-xmp-rights-index-md","assets":[{"name":"styles.0b34ffe8ec1ad9342c1f.css","size":532835},{"name":"f5cc1685-5768e2433d68321a2a75.js","size":6143},{"name":"8b61fb39-8d9d16599d59961494d7.js","size":6752},{"name":"7deef1cd-db568229c9ae5080074c.js","size":5530},{"name":"b6f3ea4c-93893a1a9cc3f7053a55.js","size":7066},{"name":"5e65052d-ab560c7f49ce6e61a438.js","size":6030},{"name":"2dee68d8-2581d4c6e40e7ba2c1af.js","size":6607},{"name":"commons-45d0b93d6f0816b185bb.js","size":103104},{"name":"component---src-pages-xmp-namespaces-xmp-rights-index-md-d019dbe0514d72f1efb0.js","size":3937}],"filteredAssets":0,"assetsSize":678004,"filteredAuxiliaryAssets":8,"auxiliaryAssetsSize":381395},"component---src-pages-xmp-namespaces-xmp-t-pg-index-md":{"name":"component---src-pages-xmp-namespaces-xmp-t-pg-index-md","assets":[{"name":"styles.0b34ffe8ec1ad9342c1f.css","size":532835},{"name":"f5cc1685-5768e2433d68321a2a75.js","size":6143},{"name":"8b61fb39-8d9d16599d59961494d7.js","size":6752},{"name":"7deef1cd-db568229c9ae5080074c.js","size":5530},{"name":"b6f3ea4c-93893a1a9cc3f7053a55.js","size":7066},{"name":"5e65052d-ab560c7f49ce6e61a438.js","size":6030},{"name":"2dee68d8-2581d4c6e40e7ba2c1af.js","size":6607},{"name":"commons-45d0b93d6f0816b185bb.js","size":103104},{"name":"component---src-pages-xmp-namespaces-xmp-t-pg-index-md-37a152e6693749ed02ee.js","size":3294}],"filteredAssets":0,"assetsSize":677361,"filteredAuxiliaryAssets":8,"auxiliaryAssetsSize":380631},"component---src-pages-xmp-specifications-index-md":{"name":"component---src-pages-xmp-specifications-index-md","assets":[{"name":"styles.0b34ffe8ec1ad9342c1f.css","size":532835},{"name":"f5cc1685-5768e2433d68321a2a75.js","size":6143},{"name":"8b61fb39-8d9d16599d59961494d7.js","size":6752},{"name":"7deef1cd-db568229c9ae5080074c.js","size":5530},{"name":"b6f3ea4c-93893a1a9cc3f7053a55.js","size":7066},{"name":"5e65052d-ab560c7f49ce6e61a438.js","size":6030},{"name":"2dee68d8-2581d4c6e40e7ba2c1af.js","size":6607},{"name":"commons-45d0b93d6f0816b185bb.js","size":103104},{"name":"component---src-pages-xmp-specifications-index-md-5ea9eaf37bff749bd234.js","size":4481}],"filteredAssets":0,"assetsSize":678548,"filteredAuxiliaryAssets":8,"auxiliaryAssetsSize":380258}},"assetsByChunkName":{"polyfill":["webpack-runtime-0a5a8a40d39bc58694b6.js","polyfill-8fca69998c1b56bb4653.js"],"app":["webpack-runtime-0a5a8a40d39bc58694b6.js","styles.0b34ffe8ec1ad9342c1f.css","framework-1fdfb31df7fb1cf2263b.js","ff106bf9-4c8aca29444178e3a710.js","bca8bde3-bec26adc296f79c6c723.js","app-dc5323cc35249e649428.js"],"component---node-modules-adobe-gatsby-theme-aio-src-pages-404-md":["styles.0b34ffe8ec1ad9342c1f.css","f5cc1685-5768e2433d68321a2a75.js","8b61fb39-8d9d16599d59961494d7.js","7deef1cd-db568229c9ae5080074c.js","b6f3ea4c-93893a1a9cc3f7053a55.js","5e65052d-ab560c7f49ce6e61a438.js","2dee68d8-2581d4c6e40e7ba2c1af.js","commons-45d0b93d6f0816b185bb.js","component---node-modules-adobe-gatsby-theme-aio-src-pages-404-md-38c54a7cc6735dfbf45d.js"],"component---src-pages-index-md":["styles.0b34ffe8ec1ad9342c1f.css","f5cc1685-5768e2433d68321a2a75.js","8b61fb39-8d9d16599d59961494d7.js","7deef1cd-db568229c9ae5080074c.js","b6f3ea4c-93893a1a9cc3f7053a55.js","5e65052d-ab560c7f49ce6e61a438.js","2dee68d8-2581d4c6e40e7ba2c1af.js","commons-45d0b93d6f0816b185bb.js","component---src-pages-index-md-0453ae767c0509a3b501.js"],"component---src-pages-xmp-namespaces-crs-index-md":["styles.0b34ffe8ec1ad9342c1f.css","f5cc1685-5768e2433d68321a2a75.js","8b61fb39-8d9d16599d59961494d7.js","7deef1cd-db568229c9ae5080074c.js","b6f3ea4c-93893a1a9cc3f7053a55.js","5e65052d-ab560c7f49ce6e61a438.js","2dee68d8-2581d4c6e40e7ba2c1af.js","commons-45d0b93d6f0816b185bb.js","component---src-pages-xmp-namespaces-crs-index-md-3a4495462ff30f9baf54.js"],"component---src-pages-xmp-namespaces-dc-index-md":["styles.0b34ffe8ec1ad9342c1f.css","f5cc1685-5768e2433d68321a2a75.js","8b61fb39-8d9d16599d59961494d7.js","7deef1cd-db568229c9ae5080074c.js","b6f3ea4c-93893a1a9cc3f7053a55.js","5e65052d-ab560c7f49ce6e61a438.js","2dee68d8-2581d4c6e40e7ba2c1af.js","commons-45d0b93d6f0816b185bb.js","component---src-pages-xmp-namespaces-dc-index-md-2b56534631f4ff9b99b0.js"],"component---src-pages-xmp-namespaces-exif-index-md":["styles.0b34ffe8ec1ad9342c1f.css","f5cc1685-5768e2433d68321a2a75.js","8b61fb39-8d9d16599d59961494d7.js","7deef1cd-db568229c9ae5080074c.js","b6f3ea4c-93893a1a9cc3f7053a55.js","5e65052d-ab560c7f49ce6e61a438.js","2dee68d8-2581d4c6e40e7ba2c1af.js","commons-45d0b93d6f0816b185bb.js","component---src-pages-xmp-namespaces-exif-index-md-6c7f781bbb7b85af0870.js"],"component---src-pages-xmp-namespaces-index-md":["styles.0b34ffe8ec1ad9342c1f.css","f5cc1685-5768e2433d68321a2a75.js","8b61fb39-8d9d16599d59961494d7.js","7deef1cd-db568229c9ae5080074c.js","b6f3ea4c-93893a1a9cc3f7053a55.js","5e65052d-ab560c7f49ce6e61a438.js","2dee68d8-2581d4c6e40e7ba2c1af.js","commons-45d0b93d6f0816b185bb.js","component---src-pages-xmp-namespaces-index-md-b63ac99758a50ca9c2e2.js"],"component---src-pages-xmp-namespaces-iptc-4-xmp-core-index-md":["styles.0b34ffe8ec1ad9342c1f.css","f5cc1685-5768e2433d68321a2a75.js","8b61fb39-8d9d16599d59961494d7.js","7deef1cd-db568229c9ae5080074c.js","b6f3ea4c-93893a1a9cc3f7053a55.js","5e65052d-ab560c7f49ce6e61a438.js","2dee68d8-2581d4c6e40e7ba2c1af.js","commons-45d0b93d6f0816b185bb.js","component---src-pages-xmp-namespaces-iptc-4-xmp-core-index-md-b0633949ccd76ac83c6d.js"],"component---src-pages-xmp-namespaces-pdf-index-md":["styles.0b34ffe8ec1ad9342c1f.css","f5cc1685-5768e2433d68321a2a75.js","8b61fb39-8d9d16599d59961494d7.js","7deef1cd-db568229c9ae5080074c.js","b6f3ea4c-93893a1a9cc3f7053a55.js","5e65052d-ab560c7f49ce6e61a438.js","2dee68d8-2581d4c6e40e7ba2c1af.js","commons-45d0b93d6f0816b185bb.js","component---src-pages-xmp-namespaces-pdf-index-md-2c5944b4eb3013016349.js"],"component---src-pages-xmp-namespaces-photoshop-index-md":["styles.0b34ffe8ec1ad9342c1f.css","f5cc1685-5768e2433d68321a2a75.js","8b61fb39-8d9d16599d59961494d7.js","7deef1cd-db568229c9ae5080074c.js","b6f3ea4c-93893a1a9cc3f7053a55.js","5e65052d-ab560c7f49ce6e61a438.js","2dee68d8-2581d4c6e40e7ba2c1af.js","commons-45d0b93d6f0816b185bb.js","component---src-pages-xmp-namespaces-photoshop-index-md-eccb62d5c0cf03936d9e.js"],"component---src-pages-xmp-namespaces-tiff-index-md":["styles.0b34ffe8ec1ad9342c1f.css","f5cc1685-5768e2433d68321a2a75.js","8b61fb39-8d9d16599d59961494d7.js","7deef1cd-db568229c9ae5080074c.js","b6f3ea4c-93893a1a9cc3f7053a55.js","5e65052d-ab560c7f49ce6e61a438.js","2dee68d8-2581d4c6e40e7ba2c1af.js","commons-45d0b93d6f0816b185bb.js","component---src-pages-xmp-namespaces-tiff-index-md-990d6895bce9153ae157.js"],"component---src-pages-xmp-namespaces-xmp-bj-index-md":["styles.0b34ffe8ec1ad9342c1f.css","f5cc1685-5768e2433d68321a2a75.js","8b61fb39-8d9d16599d59961494d7.js","7deef1cd-db568229c9ae5080074c.js","b6f3ea4c-93893a1a9cc3f7053a55.js","5e65052d-ab560c7f49ce6e61a438.js","2dee68d8-2581d4c6e40e7ba2c1af.js","commons-45d0b93d6f0816b185bb.js","component---src-pages-xmp-namespaces-xmp-bj-index-md-fed258d302f0b5df5fa7.js"],"component---src-pages-xmp-namespaces-xmp-data-types-ancestor-index-md":["styles.0b34ffe8ec1ad9342c1f.css","f5cc1685-5768e2433d68321a2a75.js","8b61fb39-8d9d16599d59961494d7.js","7deef1cd-db568229c9ae5080074c.js","b6f3ea4c-93893a1a9cc3f7053a55.js","5e65052d-ab560c7f49ce6e61a438.js","2dee68d8-2581d4c6e40e7ba2c1af.js","commons-45d0b93d6f0816b185bb.js","component---src-pages-xmp-namespaces-xmp-data-types-ancestor-index-md-0c32c298abc8b31692f7.js"],"component---src-pages-xmp-namespaces-xmp-data-types-beat-splice-stretch-index-md":["styles.0b34ffe8ec1ad9342c1f.css","f5cc1685-5768e2433d68321a2a75.js","8b61fb39-8d9d16599d59961494d7.js","7deef1cd-db568229c9ae5080074c.js","b6f3ea4c-93893a1a9cc3f7053a55.js","5e65052d-ab560c7f49ce6e61a438.js","2dee68d8-2581d4c6e40e7ba2c1af.js","commons-45d0b93d6f0816b185bb.js","component---src-pages-xmp-namespaces-xmp-data-types-beat-splice-stretch-index-md-171776fe0ce22f5103ce.js"],"component---src-pages-xmp-namespaces-xmp-data-types-cfa-pattern-index-md":["styles.0b34ffe8ec1ad9342c1f.css","f5cc1685-5768e2433d68321a2a75.js","8b61fb39-8d9d16599d59961494d7.js","7deef1cd-db568229c9ae5080074c.js","b6f3ea4c-93893a1a9cc3f7053a55.js","5e65052d-ab560c7f49ce6e61a438.js","2dee68d8-2581d4c6e40e7ba2c1af.js","commons-45d0b93d6f0816b185bb.js","component---src-pages-xmp-namespaces-xmp-data-types-cfa-pattern-index-md-c38ac3c4a9c1f9b3ca17.js"],"component---src-pages-xmp-namespaces-xmp-data-types-colorant-index-md":["styles.0b34ffe8ec1ad9342c1f.css","f5cc1685-5768e2433d68321a2a75.js","8b61fb39-8d9d16599d59961494d7.js","7deef1cd-db568229c9ae5080074c.js","b6f3ea4c-93893a1a9cc3f7053a55.js","5e65052d-ab560c7f49ce6e61a438.js","2dee68d8-2581d4c6e40e7ba2c1af.js","commons-45d0b93d6f0816b185bb.js","component---src-pages-xmp-namespaces-xmp-data-types-colorant-index-md-b70bfa6240d80b7ed50e.js"],"component---src-pages-xmp-namespaces-xmp-data-types-contact-info-index-md":["styles.0b34ffe8ec1ad9342c1f.css","f5cc1685-5768e2433d68321a2a75.js","8b61fb39-8d9d16599d59961494d7.js","7deef1cd-db568229c9ae5080074c.js","b6f3ea4c-93893a1a9cc3f7053a55.js","5e65052d-ab560c7f49ce6e61a438.js","2dee68d8-2581d4c6e40e7ba2c1af.js","commons-45d0b93d6f0816b185bb.js","component---src-pages-xmp-namespaces-xmp-data-types-contact-info-index-md-80501db09dd99c03ba5d.js"],"component---src-pages-xmp-namespaces-xmp-data-types-cue-point-param-index-md":["styles.0b34ffe8ec1ad9342c1f.css","f5cc1685-5768e2433d68321a2a75.js","8b61fb39-8d9d16599d59961494d7.js","7deef1cd-db568229c9ae5080074c.js","b6f3ea4c-93893a1a9cc3f7053a55.js","5e65052d-ab560c7f49ce6e61a438.js","2dee68d8-2581d4c6e40e7ba2c1af.js","commons-45d0b93d6f0816b185bb.js","component---src-pages-xmp-namespaces-xmp-data-types-cue-point-param-index-md-c79d002dc0b7805814b4.js"],"component---src-pages-xmp-namespaces-xmp-data-types-device-settings-index-md":["styles.0b34ffe8ec1ad9342c1f.css","f5cc1685-5768e2433d68321a2a75.js","8b61fb39-8d9d16599d59961494d7.js","7deef1cd-db568229c9ae5080074c.js","b6f3ea4c-93893a1a9cc3f7053a55.js","5e65052d-ab560c7f49ce6e61a438.js","2dee68d8-2581d4c6e40e7ba2c1af.js","commons-45d0b93d6f0816b185bb.js","component---src-pages-xmp-namespaces-xmp-data-types-device-settings-index-md-3bc80eb81bbdf60e2628.js"],"component---src-pages-xmp-namespaces-xmp-data-types-dimensions-index-md":["styles.0b34ffe8ec1ad9342c1f.css","f5cc1685-5768e2433d68321a2a75.js","8b61fb39-8d9d16599d59961494d7.js","7deef1cd-db568229c9ae5080074c.js","b6f3ea4c-93893a1a9cc3f7053a55.js","5e65052d-ab560c7f49ce6e61a438.js","2dee68d8-2581d4c6e40e7ba2c1af.js","commons-45d0b93d6f0816b185bb.js","component---src-pages-xmp-namespaces-xmp-data-types-dimensions-index-md-0657019883970b58533d.js"],"component---src-pages-xmp-namespaces-xmp-data-types-flash-index-md":["styles.0b34ffe8ec1ad9342c1f.css","f5cc1685-5768e2433d68321a2a75.js","8b61fb39-8d9d16599d59961494d7.js","7deef1cd-db568229c9ae5080074c.js","b6f3ea4c-93893a1a9cc3f7053a55.js","5e65052d-ab560c7f49ce6e61a438.js","2dee68d8-2581d4c6e40e7ba2c1af.js","commons-45d0b93d6f0816b185bb.js","component---src-pages-xmp-namespaces-xmp-data-types-flash-index-md-653ebd5152fa1ce74f5c.js"],"component---src-pages-xmp-namespaces-xmp-data-types-font-index-md":["styles.0b34ffe8ec1ad9342c1f.css","f5cc1685-5768e2433d68321a2a75.js","8b61fb39-8d9d16599d59961494d7.js","7deef1cd-db568229c9ae5080074c.js","b6f3ea4c-93893a1a9cc3f7053a55.js","5e65052d-ab560c7f49ce6e61a438.js","2dee68d8-2581d4c6e40e7ba2c1af.js","commons-45d0b93d6f0816b185bb.js","component---src-pages-xmp-namespaces-xmp-data-types-font-index-md-e38f7cb1698388dc7443.js"],"component---src-pages-xmp-namespaces-xmp-data-types-index-md":["styles.0b34ffe8ec1ad9342c1f.css","f5cc1685-5768e2433d68321a2a75.js","8b61fb39-8d9d16599d59961494d7.js","7deef1cd-db568229c9ae5080074c.js","b6f3ea4c-93893a1a9cc3f7053a55.js","5e65052d-ab560c7f49ce6e61a438.js","2dee68d8-2581d4c6e40e7ba2c1af.js","commons-45d0b93d6f0816b185bb.js","component---src-pages-xmp-namespaces-xmp-data-types-index-md-b7af4798a9188a6c19a4.js"],"component---src-pages-xmp-namespaces-xmp-data-types-job-index-md":["styles.0b34ffe8ec1ad9342c1f.css","f5cc1685-5768e2433d68321a2a75.js","8b61fb39-8d9d16599d59961494d7.js","7deef1cd-db568229c9ae5080074c.js","b6f3ea4c-93893a1a9cc3f7053a55.js","5e65052d-ab560c7f49ce6e61a438.js","2dee68d8-2581d4c6e40e7ba2c1af.js","commons-45d0b93d6f0816b185bb.js","component---src-pages-xmp-namespaces-xmp-data-types-job-index-md-3a4fed1c939d17a41bca.js"],"component---src-pages-xmp-namespaces-xmp-data-types-layer-index-md":["styles.0b34ffe8ec1ad9342c1f.css","f5cc1685-5768e2433d68321a2a75.js","8b61fb39-8d9d16599d59961494d7.js","7deef1cd-db568229c9ae5080074c.js","b6f3ea4c-93893a1a9cc3f7053a55.js","5e65052d-ab560c7f49ce6e61a438.js","2dee68d8-2581d4c6e40e7ba2c1af.js","commons-45d0b93d6f0816b185bb.js","component---src-pages-xmp-namespaces-xmp-data-types-layer-index-md-b063958500c95872d8a0.js"],"component---src-pages-xmp-namespaces-xmp-data-types-marker-index-md":["styles.0b34ffe8ec1ad9342c1f.css","f5cc1685-5768e2433d68321a2a75.js","8b61fb39-8d9d16599d59961494d7.js","7deef1cd-db568229c9ae5080074c.js","b6f3ea4c-93893a1a9cc3f7053a55.js","5e65052d-ab560c7f49ce6e61a438.js","2dee68d8-2581d4c6e40e7ba2c1af.js","commons-45d0b93d6f0816b185bb.js","component---src-pages-xmp-namespaces-xmp-data-types-marker-index-md-a98ef0c3e796066b8dc5.js"],"component---src-pages-xmp-namespaces-xmp-data-types-media-index-md":["styles.0b34ffe8ec1ad9342c1f.css","f5cc1685-5768e2433d68321a2a75.js","8b61fb39-8d9d16599d59961494d7.js","7deef1cd-db568229c9ae5080074c.js","b6f3ea4c-93893a1a9cc3f7053a55.js","5e65052d-ab560c7f49ce6e61a438.js","2dee68d8-2581d4c6e40e7ba2c1af.js","commons-45d0b93d6f0816b185bb.js","component---src-pages-xmp-namespaces-xmp-data-types-media-index-md-5c95f599fbc1dbed5ced.js"],"component---src-pages-xmp-namespaces-xmp-data-types-oecf-sfr-index-md":["styles.0b34ffe8ec1ad9342c1f.css","f5cc1685-5768e2433d68321a2a75.js","8b61fb39-8d9d16599d59961494d7.js","7deef1cd-db568229c9ae5080074c.js","b6f3ea4c-93893a1a9cc3f7053a55.js","5e65052d-ab560c7f49ce6e61a438.js","2dee68d8-2581d4c6e40e7ba2c1af.js","commons-45d0b93d6f0816b185bb.js","component---src-pages-xmp-namespaces-xmp-data-types-oecf-sfr-index-md-351f87403fcc92456b6c.js"],"component---src-pages-xmp-namespaces-xmp-data-types-project-link-index-md":["styles.0b34ffe8ec1ad9342c1f.css","f5cc1685-5768e2433d68321a2a75.js","8b61fb39-8d9d16599d59961494d7.js","7deef1cd-db568229c9ae5080074c.js","b6f3ea4c-93893a1a9cc3f7053a55.js","5e65052d-ab560c7f49ce6e61a438.js","2dee68d8-2581d4c6e40e7ba2c1af.js","commons-45d0b93d6f0816b185bb.js","component---src-pages-xmp-namespaces-xmp-data-types-project-link-index-md-7a8f6389f419a346d751.js"],"component---src-pages-xmp-namespaces-xmp-data-types-resample-stretch-index-md":["styles.0b34ffe8ec1ad9342c1f.css","f5cc1685-5768e2433d68321a2a75.js","8b61fb39-8d9d16599d59961494d7.js","7deef1cd-db568229c9ae5080074c.js","b6f3ea4c-93893a1a9cc3f7053a55.js","5e65052d-ab560c7f49ce6e61a438.js","2dee68d8-2581d4c6e40e7ba2c1af.js","commons-45d0b93d6f0816b185bb.js","component---src-pages-xmp-namespaces-xmp-data-types-resample-stretch-index-md-b7b4981255b4b1b22f57.js"],"component---src-pages-xmp-namespaces-xmp-data-types-resource-event-index-md":["styles.0b34ffe8ec1ad9342c1f.css","f5cc1685-5768e2433d68321a2a75.js","8b61fb39-8d9d16599d59961494d7.js","7deef1cd-db568229c9ae5080074c.js","b6f3ea4c-93893a1a9cc3f7053a55.js","5e65052d-ab560c7f49ce6e61a438.js","2dee68d8-2581d4c6e40e7ba2c1af.js","commons-45d0b93d6f0816b185bb.js","component---src-pages-xmp-namespaces-xmp-data-types-resource-event-index-md-0a1153b9b86a3e2c0ba2.js"],"component---src-pages-xmp-namespaces-xmp-data-types-resource-ref-index-md":["styles.0b34ffe8ec1ad9342c1f.css","f5cc1685-5768e2433d68321a2a75.js","8b61fb39-8d9d16599d59961494d7.js","7deef1cd-db568229c9ae5080074c.js","b6f3ea4c-93893a1a9cc3f7053a55.js","5e65052d-ab560c7f49ce6e61a438.js","2dee68d8-2581d4c6e40e7ba2c1af.js","commons-45d0b93d6f0816b185bb.js","component---src-pages-xmp-namespaces-xmp-data-types-resource-ref-index-md-391552cc029c1f71d0c5.js"],"component---src-pages-xmp-namespaces-xmp-data-types-thumbnails-index-md":["styles.0b34ffe8ec1ad9342c1f.css","f5cc1685-5768e2433d68321a2a75.js","8b61fb39-8d9d16599d59961494d7.js","7deef1cd-db568229c9ae5080074c.js","b6f3ea4c-93893a1a9cc3f7053a55.js","5e65052d-ab560c7f49ce6e61a438.js","2dee68d8-2581d4c6e40e7ba2c1af.js","commons-45d0b93d6f0816b185bb.js","component---src-pages-xmp-namespaces-xmp-data-types-thumbnails-index-md-ffc3fb5ab5e0ba996685.js"],"component---src-pages-xmp-namespaces-xmp-data-types-time-index-md":["styles.0b34ffe8ec1ad9342c1f.css","f5cc1685-5768e2433d68321a2a75.js","8b61fb39-8d9d16599d59961494d7.js","7deef1cd-db568229c9ae5080074c.js","b6f3ea4c-93893a1a9cc3f7053a55.js","5e65052d-ab560c7f49ce6e61a438.js","2dee68d8-2581d4c6e40e7ba2c1af.js","commons-45d0b93d6f0816b185bb.js","component---src-pages-xmp-namespaces-xmp-data-types-time-index-md-494717b08aa09388c84c.js"],"component---src-pages-xmp-namespaces-xmp-data-types-time-scale-stretch-index-md":["styles.0b34ffe8ec1ad9342c1f.css","f5cc1685-5768e2433d68321a2a75.js","8b61fb39-8d9d16599d59961494d7.js","7deef1cd-db568229c9ae5080074c.js","b6f3ea4c-93893a1a9cc3f7053a55.js","5e65052d-ab560c7f49ce6e61a438.js","2dee68d8-2581d4c6e40e7ba2c1af.js","commons-45d0b93d6f0816b185bb.js","component---src-pages-xmp-namespaces-xmp-data-types-time-scale-stretch-index-md-ae2b8c9f55aa537258b1.js"],"component---src-pages-xmp-namespaces-xmp-data-types-timecode-index-md":["styles.0b34ffe8ec1ad9342c1f.css","f5cc1685-5768e2433d68321a2a75.js","8b61fb39-8d9d16599d59961494d7.js","7deef1cd-db568229c9ae5080074c.js","b6f3ea4c-93893a1a9cc3f7053a55.js","5e65052d-ab560c7f49ce6e61a438.js","2dee68d8-2581d4c6e40e7ba2c1af.js","commons-45d0b93d6f0816b185bb.js","component---src-pages-xmp-namespaces-xmp-data-types-timecode-index-md-e70b16e2e55b047c4184.js"],"component---src-pages-xmp-namespaces-xmp-data-types-track-index-md":["styles.0b34ffe8ec1ad9342c1f.css","f5cc1685-5768e2433d68321a2a75.js","8b61fb39-8d9d16599d59961494d7.js","7deef1cd-db568229c9ae5080074c.js","b6f3ea4c-93893a1a9cc3f7053a55.js","5e65052d-ab560c7f49ce6e61a438.js","2dee68d8-2581d4c6e40e7ba2c1af.js","commons-45d0b93d6f0816b185bb.js","component---src-pages-xmp-namespaces-xmp-data-types-track-index-md-b70ef51e0a9a06884d06.js"],"component---src-pages-xmp-namespaces-xmp-data-types-version-index-md":["styles.0b34ffe8ec1ad9342c1f.css","f5cc1685-5768e2433d68321a2a75.js","8b61fb39-8d9d16599d59961494d7.js","7deef1cd-db568229c9ae5080074c.js","b6f3ea4c-93893a1a9cc3f7053a55.js","5e65052d-ab560c7f49ce6e61a438.js","2dee68d8-2581d4c6e40e7ba2c1af.js","commons-45d0b93d6f0816b185bb.js","component---src-pages-xmp-namespaces-xmp-data-types-version-index-md-df93db3a06bb688f7bbb.js"],"component---src-pages-xmp-namespaces-xmp-dm-index-md":["styles.0b34ffe8ec1ad9342c1f.css","f5cc1685-5768e2433d68321a2a75.js","8b61fb39-8d9d16599d59961494d7.js","7deef1cd-db568229c9ae5080074c.js","b6f3ea4c-93893a1a9cc3f7053a55.js","5e65052d-ab560c7f49ce6e61a438.js","2dee68d8-2581d4c6e40e7ba2c1af.js","commons-45d0b93d6f0816b185bb.js","component---src-pages-xmp-namespaces-xmp-dm-index-md-09875a239b84bead8d34.js"],"component---src-pages-xmp-namespaces-xmp-index-md":["styles.0b34ffe8ec1ad9342c1f.css","f5cc1685-5768e2433d68321a2a75.js","8b61fb39-8d9d16599d59961494d7.js","7deef1cd-db568229c9ae5080074c.js","b6f3ea4c-93893a1a9cc3f7053a55.js","5e65052d-ab560c7f49ce6e61a438.js","2dee68d8-2581d4c6e40e7ba2c1af.js","commons-45d0b93d6f0816b185bb.js","component---src-pages-xmp-namespaces-xmp-index-md-3837f28aee7828a8bd75.js"],"component---src-pages-xmp-namespaces-xmp-mm-index-md":["styles.0b34ffe8ec1ad9342c1f.css","f5cc1685-5768e2433d68321a2a75.js","8b61fb39-8d9d16599d59961494d7.js","7deef1cd-db568229c9ae5080074c.js","b6f3ea4c-93893a1a9cc3f7053a55.js","5e65052d-ab560c7f49ce6e61a438.js","2dee68d8-2581d4c6e40e7ba2c1af.js","commons-45d0b93d6f0816b185bb.js","component---src-pages-xmp-namespaces-xmp-mm-index-md-babc619e51757d629231.js"],"component---src-pages-xmp-namespaces-xmp-rights-index-md":["styles.0b34ffe8ec1ad9342c1f.css","f5cc1685-5768e2433d68321a2a75.js","8b61fb39-8d9d16599d59961494d7.js","7deef1cd-db568229c9ae5080074c.js","b6f3ea4c-93893a1a9cc3f7053a55.js","5e65052d-ab560c7f49ce6e61a438.js","2dee68d8-2581d4c6e40e7ba2c1af.js","commons-45d0b93d6f0816b185bb.js","component---src-pages-xmp-namespaces-xmp-rights-index-md-d019dbe0514d72f1efb0.js"],"component---src-pages-xmp-namespaces-xmp-t-pg-index-md":["styles.0b34ffe8ec1ad9342c1f.css","f5cc1685-5768e2433d68321a2a75.js","8b61fb39-8d9d16599d59961494d7.js","7deef1cd-db568229c9ae5080074c.js","b6f3ea4c-93893a1a9cc3f7053a55.js","5e65052d-ab560c7f49ce6e61a438.js","2dee68d8-2581d4c6e40e7ba2c1af.js","commons-45d0b93d6f0816b185bb.js","component---src-pages-xmp-namespaces-xmp-t-pg-index-md-37a152e6693749ed02ee.js"],"component---src-pages-xmp-specifications-index-md":["styles.0b34ffe8ec1ad9342c1f.css","f5cc1685-5768e2433d68321a2a75.js","8b61fb39-8d9d16599d59961494d7.js","7deef1cd-db568229c9ae5080074c.js","b6f3ea4c-93893a1a9cc3f7053a55.js","5e65052d-ab560c7f49ce6e61a438.js","2dee68d8-2581d4c6e40e7ba2c1af.js","commons-45d0b93d6f0816b185bb.js","component---src-pages-xmp-specifications-index-md-5ea9eaf37bff749bd234.js"]},"childAssetsByChunkName":{}}